config/__init__.py
config/settings.py
database/__init__.py
database/connection.py
exceptions/base.py
schemas/__init__.py
schemas/comment.py
schemas/followers.py
schemas/friends.py
schemas/history.py
schemas/like.py
schemas/media.py
schemas/message.py
schemas/response.py
schemas/role.py
schemas/token.py
schemas/user.py
syrup_shared-0.1.0.dist-info/licenses/LICENSE
utils/__init__.py
utils/cookie.py
utils/file_utils.py
utils/json_utils.py
utils/jwt.py
utils/logger.py
utils/validation.py
syrup_shared-0.1.0.dist-info/METADATA
syrup_shared-0.1.0.dist-info/WHEEL
syrup_shared-0.1.0.dist-info/top_level.txt
syrup_shared-0.1.0.dist-info/RECORD
