Metadata-Version: 2.4
Name: syrup-shared
Version: 0.1.0
Summary: Shared components library for SYRUP microservices
Author-email: SYRUP Team <team@syrup.dev>
Maintainer-email: SYRUP Team <team@syrup.dev>
License: MIT
Project-URL: Homepage, https://github.com/syrup-team/syrup-shared
Project-URL: Documentation, https://github.com/syrup-team/syrup-shared#readme
Project-URL: Repository, https://github.com/syrup-team/syrup-shared.git
Project-URL: Bug Tracker, https://github.com/syrup-team/syrup-shared/issues
Keywords: fastapi,microservices,shared,database,jwt,pydantic
Classifier: Development Status :: 3 - Alpha
Classifier: Intended Audience :: Developers
Classifier: License :: OSI Approved :: MIT License
Classifier: Programming Language :: Python :: 3
Classifier: Programming Language :: Python :: 3.9
Classifier: Programming Language :: Python :: 3.10
Classifier: Programming Language :: Python :: 3.11
Classifier: Programming Language :: Python :: 3.12
Classifier: Topic :: Software Development :: Libraries :: Python Modules
Classifier: Topic :: Internet :: WWW/HTTP :: HTTP Servers
Classifier: Framework :: FastAPI
Requires-Python: >=3.9
License-File: LICENSE
Requires-Dist: fastapi>=0.115.0
Requires-Dist: sqlalchemy>=2.0
Requires-Dist: aiosqlite>=0.21.0
Requires-Dist: pydantic>=2.11.0
Requires-Dist: pydantic-settings>=2.10.0
Requires-Dist: python-jose[cryptography]>=3.4.0
Requires-Dist: passlib[bcrypt]>=1.7.4
Requires-Dist: bcrypt>=4.2.1
Requires-Dist: colorlog>=6.9.0
Requires-Dist: redis>=5.2.0
Requires-Dist: boto3>=1.37.0
Requires-Dist: pillow>=11.0.0
Requires-Dist: aiohttp>=3.9.0
Requires-Dist: httpx>=0.27.0
Requires-Dist: requests>=2.31.0
Provides-Extra: dev
Requires-Dist: pytest>=7.0.0; extra == "dev"
Requires-Dist: pytest-asyncio>=0.21.0; extra == "dev"
Requires-Dist: black>=23.0.0; extra == "dev"
Requires-Dist: isort>=5.12.0; extra == "dev"
Requires-Dist: flake8>=6.0.0; extra == "dev"
Requires-Dist: mypy>=1.0.0; extra == "dev"
Provides-Extra: test
Requires-Dist: pytest>=7.0.0; extra == "test"
Requires-Dist: pytest-asyncio>=0.21.0; extra == "test"
Requires-Dist: httpx>=0.27.0; extra == "test"
Dynamic: license-file
